kimi_cli/CHANGELOG.md
kimi_cli/__init__.py
kimi_cli/acp/AGENTS.md
kimi_cli/acp/__init__.py
kimi_cli/acp/convert.py
kimi_cli/acp/kaos.py
kimi_cli/acp/mcp.py
kimi_cli/acp/server.py
kimi_cli/acp/session.py
kimi_cli/acp/tools.py
kimi_cli/acp/types.py
kimi_cli/agents/default/agent.yaml
kimi_cli/agents/default/sub.yaml
kimi_cli/agents/default/system.md
kimi_cli/agents/okabe/agent.yaml
kimi_cli/agentspec.py
kimi_cli/app.py
kimi_cli/auth/__init__.py
kimi_cli/auth/oauth.py
kimi_cli/auth/platforms.py
kimi_cli/cli/__init__.py
kimi_cli/cli/__main__.py
kimi_cli/cli/info.py
kimi_cli/cli/mcp.py
kimi_cli/cli/toad.py
kimi_cli/cli/web.py
kimi_cli/config.py
kimi_cli/constant.py
kimi_cli/exception.py
kimi_cli/llm.py
kimi_cli/metadata.py
kimi_cli/prompts/__init__.py
kimi_cli/prompts/compact.md
kimi_cli/prompts/init.md
kimi_cli/py.typed
kimi_cli/session.py
kimi_cli/share.py
kimi_cli/skill/__init__.py
kimi_cli/skill/flow/__init__.py
kimi_cli/skill/flow/d2.py
kimi_cli/skill/flow/mermaid.py
kimi_cli/skills/kimi-cli-help/SKILL.md
kimi_cli/skills/skill-creator/SKILL.md
kimi_cli/soul/__init__.py
kimi_cli/soul/agent.py
kimi_cli/soul/approval.py
kimi_cli/soul/compaction.py
kimi_cli/soul/context.py
kimi_cli/soul/denwarenji.py
kimi_cli/soul/kimisoul.py
kimi_cli/soul/message.py
kimi_cli/soul/slash.py
kimi_cli/soul/toolset.py
kimi_cli/tools/AGENTS.md
kimi_cli/tools/__init__.py
kimi_cli/tools/display.py
kimi_cli/tools/dmail/__init__.py
kimi_cli/tools/dmail/dmail.md
kimi_cli/tools/file/__init__.py
kimi_cli/tools/file/glob.md
kimi_cli/tools/file/glob.py
kimi_cli/tools/file/grep.md
kimi_cli/tools/file/grep_local.py
kimi_cli/tools/file/read.md
kimi_cli/tools/file/read.py
kimi_cli/tools/file/read_media.md
kimi_cli/tools/file/read_media.py
kimi_cli/tools/file/replace.md
kimi_cli/tools/file/replace.py
kimi_cli/tools/file/utils.py
kimi_cli/tools/file/write.md
kimi_cli/tools/file/write.py
kimi_cli/tools/multiagent/__init__.py
kimi_cli/tools/multiagent/create.md
kimi_cli/tools/multiagent/create.py
kimi_cli-1.5.dist-info/WHEEL
kimi_cli-1.5.dist-info/entry_points.txt
kimi_cli-1.5.dist-info/METADATA
kimi_cli-1.5.dist-info/RECORD
