Metadata-Version: 2.3
Name: kimi-cli
Version: 1.5
Summary: Kimi Code CLI is your next CLI agent.
Requires-Dist: agent-client-protocol==0.7.0
Requires-Dist: aiofiles>=24.0,<26.0
Requires-Dist: aiohttp==3.13.3
Requires-Dist: typer==0.21.1
Requires-Dist: kosong[contrib]==0.41.0
Requires-Dist: loguru>=0.6.0,<0.8
Requires-Dist: prompt-toolkit==3.0.52
Requires-Dist: pillow==12.1.0
Requires-Dist: pyyaml==6.0.3
Requires-Dist: rich==14.2.0
Requires-Dist: ripgrepy==2.2.0
Requires-Dist: streamingjson==0.0.5
Requires-Dist: trafilatura==2.0.0
Requires-Dist: lxml==6.0.2
Requires-Dist: tenacity==9.1.2
Requires-Dist: fastmcp==2.12.5
Requires-Dist: pydantic==2.12.5
Requires-Dist: httpx[socks]==0.28.1
Requires-Dist: pykaos==0.6.0
Requires-Dist: batrachian-toad==0.5.23 ; python_full_version >= '3.14'
Requires-Dist: tomlkit==0.14.0
Requires-Dist: jinja2==3.1.6
Requires-Dist: pyobjc-framework-cocoa>=12.1 ; sys_platform == 'darwin'
Requires-Dist: fastapi>=0.115.0
Requires-Dist: uvicorn[standard]>=0.32.0
Requires-Dist: scalar-fastapi>=1.5.0
Requires-Dist: websockets>=14.0
Requires-Dist: keyring>=25.7.0
Requires-Python: >=3.12
